lstack/__init__.py
lstack-1.1.1.dist-info/LICENSE
lstack-1.1.1.dist-info/METADATA
lstack-1.1.1.dist-info/WHEEL
lstack-1.1.1.dist-info/top_level.txt
lstack-1.1.1.dist-info/RECORD
