Metadata-Version: 2.1
Name: lstack
Version: 1.1.1
Summary: Sophisticate Linked Stack
Home-page: https://pypi.org/project/lstack/
Author: khiat Mohammed Abderrezzak
Author-email: khiat.dev@gmail.com
License: MIT
Keywords: linked stack
Classifier: Programming Language :: Python :: 3
Classifier: Operating System :: OS Independent
Classifier: License :: OSI Approved :: MIT License
Requires-Python: >=3.6
License-File: LICENSE
Requires-Dist: linkedit (>=1.1.3)
